.gitignore
LICENSE
MANIFEST.in
README.md
pyproject.toml
pycfit/__init__.py
pycfit/_api.py
pycfit/_dialog.py
pycfit/_dialog_grid.py
pycfit/_function.py
pycfit/_grid.py
pycfit/_help_text.py
pycfit/_settings.py
pycfit/_util.py
pycfit/_version.py
pycfit/version.py
pycfit.egg-info/PKG-INFO
pycfit.egg-info/SOURCES.txt
pycfit.egg-info/dependency_links.txt
pycfit.egg-info/not-zip-safe
pycfit.egg-info/requires.txt
pycfit.egg-info/top_level.txt
pycfit/data/__init__.py
pycfit/data/avg_data.npz
pycfit/data/grid_data.npz
pycfit/data/patch_data.npz
pycfit/docs/pyCFIT_User_Guide.pdf
pycfit/ui/AdjustComponent.ui
pycfit/ui/Fit.ui
pycfit/ui/GridFit.ui
pycfit/ui/MaskedPoints.ui
pycfit/ui/NewComponent.ui
pycfit/ui/Parameter.ui
saved_files/ayris.py
saved_files/ayris2.py
saved_files/model3el.py
saved_files/modelNoTie.py
saved_files/modelTied.py
tests/run_test.py