Metadata-Version: 2.4
Name: pycfit
Version: 1.0.0
Summary: Component Fitting package
Author-email: Ayris Narock <ayris.a.narock@nasa.gov>
License-Expression: Apache-2.0
Project-URL: source, https://git.smce.nasa.gov/solo/pycfit
Classifier: Development Status :: 4 - Beta
Requires-Python: >=3.11
License-File: LICENSE
Requires-Dist: astropy[recommended]>=7.1
Requires-Dist: setuptools
Requires-Dist: dask
Requires-Dist: asdf-astropy>=0.3
Requires-Dist: PyQt5
Requires-Dist: qtpy
Requires-Dist: pyqtspinner
Requires-Dist: pyqtgraph
Dynamic: license-file
